README.rst
setup.py
cqujwc/__init__.py
cqujwc.egg-info/PKG-INFO
cqujwc.egg-info/SOURCES.txt
cqujwc.egg-info/dependency_links.txt
cqujwc.egg-info/requires.txt
cqujwc.egg-info/top_level.txt