Metadata-Version: 1.0
Name: cqujwc
Version: 0.0.7
Summary: 重庆大学教务处登录模块
Home-page: https://github.com/maxoyed-MS/cqu_jwc
Author: maxoyed
Author-email: maxoyed@gmail.com
License: GPL License
Keywords: spider cqu jwc
Platform: any
